{
  "items": [
    {
      "id": "1",
      "checked": false,
      "item": "Visit balachandra.in"
    },
    {
      "id": "3",
      "checked": false,
      "item": "AI"
    },
    {
      "id": "5",
      "checked": false,
      "item": "grow money"
    },
    {
      "id": "6",
      "checked": true,
      "item": "take bath"
    },
    {
      "id": "7",
      "checked": false,
      "item": "give money"
    },
    {
      "id": 8,
      "checked": false,
      "item": "call me"
    }
  ]
}
